tradingview_alert/__init__.py
tradingview_alert/tv.py
tradingview_alert-0.0.1.dist-info/LICENSE
tradingview_alert-0.0.1.dist-info/METADATA
tradingview_alert-0.0.1.dist-info/WHEEL
tradingview_alert-0.0.1.dist-info/top_level.txt
tradingview_alert-0.0.1.dist-info/RECORD
